domdf_python_tools/__init__.py
domdf_python_tools/_is_match.py
domdf_python_tools/bases.py
domdf_python_tools/dates.py
domdf_python_tools/delegators.py
domdf_python_tools/doctools.py
domdf_python_tools/getters.py
domdf_python_tools/google-10000-english-no-swears.txt
domdf_python_tools/import_tools.py
domdf_python_tools/iterative.py
domdf_python_tools/paths.py
domdf_python_tools/pretty_print.py
domdf_python_tools/py.typed
domdf_python_tools/secrets.py
domdf_python_tools/stringlist.py
domdf_python_tools/terminal.py
domdf_python_tools/typing.py
domdf_python_tools/utils.py
domdf_python_tools/versions.py
domdf_python_tools/words.py
domdf_python_tools/compat/__init__.py
domdf_python_tools/compat/importlib_metadata.py
domdf_python_tools/compat/importlib_metadata.pyi
domdf_python_tools/compat/importlib_resources.py
domdf_python_tools/compat/importlib_resources.pyi
domdf_python_tools/pagesizes/__init__.py
domdf_python_tools/pagesizes/classes.py
domdf_python_tools/pagesizes/sizes.py
domdf_python_tools/pagesizes/units.py
domdf_python_tools/pagesizes/utils.py
domdf_python_tools-3.9.0.dist-info/LICENSE
domdf_python_tools-3.9.0.dist-info/METADATA
domdf_python_tools-3.9.0.dist-info/WHEEL
domdf_python_tools-3.9.0.dist-info/top_level.txt
domdf_python_tools-3.9.0.dist-info/RECORD
