Metadata-Version: 2.1
Name: domdf_python_tools
Version: 3.9.0
Summary: Helpful functions for Python 🐍 🛠️
Home-page: https://github.com/domdfcoding/domdf_python_tools
Author: Dominic Davis-Foster
Author-email: Dominic Davis-Foster <dominic@davis-foster.co.uk>
License: Copyright (c) 2019-2022 Dominic Davis-Foster
Project-URL: Homepage, https://github.com/domdfcoding/domdf_python_tools
Project-URL: Issue Tracker, https://github.com/domdfcoding/domdf_python_tools/issues
Project-URL: Source Code, https://github.com/domdfcoding/domdf_python_tools
Project-URL: Documentation, https://domdf-python-tools.readthedocs.io/en/latest
Keywords: utilities
Platform: Windows
Platform: macOS
Platform: Linux
Classifier: Development Status :: 5 - Production/Stable
Classifier: Intended Audience :: Developers
Classifier: License :: OSI Approved :: MIT License
Classifier: Operating System :: OS Independent
Classifier: Programming Language :: Python
Classifier: Programming Language :: Python :: 3 :: Only
Classifier: Programming Language :: Python :: 3.6
Classifier: Programming Language :: Python :: 3.7
Classifier: Programming Language :: Python :: 3.8
Classifier: Programming Language :: Python :: 3.9
Classifier: Programming Language :: Python :: 3.10
Classifier: Programming Language :: Python :: 3.11
Classifier: Programming Language :: Python :: 3.12
Classifier: Programming Language :: Python :: Implementation :: CPython
Classifier: Programming Language :: Python :: Implementation :: PyPy
Classifier: Topic :: Software Development :: Libraries :: Python Modules
Classifier: Typing :: Typed
Requires-Python: >=3.6
Provides-Extra: dates
Provides-Extra: testing
Provides-Extra: all
License-File: LICENSE
